{
	"backtrace" : 1,
	"backtraceGraph" : 
	{
		"commands" : 
		[
			"add_library"
		],
		"files" : 
		[
			"CMakeLists.txt"
		],
		"nodes" : 
		[
			{
				"file" : 0
			},
			{
				"command" : 0,
				"file" : 0,
				"line" : 43,
				"parent" : 0
			}
		]
	},
	"id" : "catch2::@6890427a1f51a3e7e1df",
	"name" : "catch2",
	"paths" : 
	{
		"build" : ".",
		"source" : "."
	},
	"sourceGroups" : 
	[
		{
			"name" : "Source Files",
			"sourceIndexes" : 
			[
				0,
				1
			]
		},
		{
			"name" : "Header Files",
			"sourceIndexes" : 
			[
				2
			]
		}
	],
	"sources" : 
	[
		{
			"backtrace" : 1,
			"path" : "tests/particle_test.cc",
			"sourceGroupIndex" : 0
		},
		{
			"backtrace" : 1,
			"path" : "src/particle.cc",
			"sourceGroupIndex" : 0
		},
		{
			"backtrace" : 1,
			"path" : "include/particle.h",
			"sourceGroupIndex" : 1
		}
	],
	"type" : "INTERFACE_LIBRARY"
}
